Metadata-Version: 2.4
Name: STONKZILLA
Version: 0.1.6
Summary: Market price and indicator plotter.
Author-email: Jakub Gąsior <jakubgasior72@gmail.com>
License: MIT
Requires-Python: >=3.13.3
License-File: LICENSE
Requires-Dist: annotated-types==0.7.0; python_version >= "3.8"
Requires-Dist: astroid==3.3.9; python_full_version >= "3.9.0"
Requires-Dist: beautifulsoup4==4.13.4; python_full_version >= "3.7.0"
Requires-Dist: certifi==2025.4.26; python_version >= "3.6"
Requires-Dist: cffi==1.17.1; python_version >= "3.8"
Requires-Dist: charset-normalizer==3.4.2; python_version >= "3.7"
Requires-Dist: click==8.1.8; python_version >= "3.7"
Requires-Dist: contourpy==1.3.2; python_version >= "3.10"
Requires-Dist: curl-cffi==0.10.0; python_version >= "3.9"
Requires-Dist: cycler==0.12.1; python_version >= "3.8"
Requires-Dist: dill==0.4.0; python_version >= "3.8"
Requires-Dist: fonttools==4.57.0; python_version >= "3.8"
Requires-Dist: frozendict==2.4.6; python_version >= "3.6"
Requires-Dist: idna==3.10; python_version >= "3.6"
Requires-Dist: isort==6.0.1; python_full_version >= "3.9.0"
Requires-Dist: kiwisolver==1.4.8; python_version >= "3.10"
Requires-Dist: matplotlib==3.10.1; python_version >= "3.10"
Requires-Dist: mccabe==0.7.0; python_version >= "3.6"
Requires-Dist: multitasking==0.0.11
Requires-Dist: numpy==2.2.5; python_version >= "3.10"
Requires-Dist: packaging==25.0; python_version >= "3.8"
Requires-Dist: pandas==2.2.3; python_version >= "3.9"
Requires-Dist: peewee==3.18.1
Requires-Dist: pillow==11.2.1; python_version >= "3.9"
Requires-Dist: platformdirs==4.3.8; python_version >= "3.9"
Requires-Dist: pycparser==2.22; python_version >= "3.8"
Requires-Dist: pydantic==2.11.4; python_version >= "3.9"
Requires-Dist: pydantic-core==2.33.2; python_version >= "3.9"
Requires-Dist: pyparsing==3.2.3; python_version >= "3.9"
Requires-Dist: python-dateutil==2.9.0.post0; python_version >= "2.7" and python_version not in "3.0, 3.1, 3.2"
Requires-Dist: pytz==2025.2
Requires-Dist: pyyaml==6.0.2; python_version >= "3.8"
Requires-Dist: requests==2.32.3; python_version >= "3.8"
Requires-Dist: six==1.17.0; python_version >= "2.7" and python_version not in "3.0, 3.1, 3.2"
Requires-Dist: soupsieve==2.7; python_version >= "3.8"
Requires-Dist: tomlkit==0.13.2; python_version >= "3.8"
Requires-Dist: typing-extensions==4.13.2; python_version >= "3.8"
Requires-Dist: typing-inspection==0.4.0; python_version >= "3.9"
Requires-Dist: tzdata==2025.2; python_version >= "2"
Requires-Dist: urllib3==2.4.0; python_version >= "3.9"
Requires-Dist: yfinance==0.2.58
Dynamic: license-file
